fuzzy_dl_owl2/__init__.py
fuzzy_dl_owl2/fuzzydl/__init__.py
fuzzy_dl_owl2/fuzzydl/assertion/__init__.py
fuzzy_dl_owl2/fuzzydl/assertion/assertion.py
fuzzy_dl_owl2/fuzzydl/assertion/atomic_assertion.py
fuzzy_dl_owl2/fuzzydl/classification_node.py
fuzzy_dl_owl2/fuzzydl/concept/__init__.py
fuzzy_dl_owl2/fuzzydl/concept/all_some_concept.py
fuzzy_dl_owl2/fuzzydl/concept/approximation_concept.py
fuzzy_dl_owl2/fuzzydl/concept/atomic_concept.py
fuzzy_dl_owl2/fuzzydl/concept/choquet_integral.py
fuzzy_dl_owl2/fuzzydl/concept/concept.py
fuzzy_dl_owl2/fuzzydl/concept/concrete/__init__.py
fuzzy_dl_owl2/fuzzydl/concept/concrete/crisp_concrete_concept.py
fuzzy_dl_owl2/fuzzydl/concept/concrete/fuzzy_concrete_concept.py
fuzzy_dl_owl2/fuzzydl/concept/concrete/fuzzy_number/__init__.py
fuzzy_dl_owl2/fuzzydl/concept/concrete/fuzzy_number/triangular_fuzzy_number.py
fuzzy_dl_owl2/fuzzydl/concept/concrete/left_concrete_concept.py
fuzzy_dl_owl2/fuzzydl/concept/concrete/linear_concrete_concept.py
fuzzy_dl_owl2/fuzzydl/concept/concrete/modified_concrete_concept.py
fuzzy_dl_owl2/fuzzydl/concept/concrete/right_concrete_concept.py
fuzzy_dl_owl2/fuzzydl/concept/concrete/trapezoidal_concrete_concept.py
fuzzy_dl_owl2/fuzzydl/concept/concrete/triangular_concrete_concept.py
fuzzy_dl_owl2/fuzzydl/concept/ext_threshold_concept.py
fuzzy_dl_owl2/fuzzydl/concept/has_value_concept.py
fuzzy_dl_owl2/fuzzydl/concept/implies_concept.py
fuzzy_dl_owl2/fuzzydl/concept/interface/__init__.py
fuzzy_dl_owl2/fuzzydl/concept/interface/has_concept_interface.py
fuzzy_dl_owl2/fuzzydl/concept/interface/has_concepts_interface.py
fuzzy_dl_owl2/fuzzydl/concept/interface/has_role_concept_interface.py
fuzzy_dl_owl2/fuzzydl/concept/interface/has_role_interface.py
fuzzy_dl_owl2/fuzzydl/concept/interface/has_value_interface.py
fuzzy_dl_owl2/fuzzydl/concept/interface/has_weighted_concepts_interface.py
fuzzy_dl_owl2/fuzzydl/concept/modified/__init__.py
fuzzy_dl_owl2/fuzzydl/concept/modified/linearly_modified_concept.py
fuzzy_dl_owl2-1.0.9.dist-info/LICENSE
fuzzy_dl_owl2-1.0.9.dist-info/METADATA
fuzzy_dl_owl2-1.0.9.dist-info/WHEEL
fuzzy_dl_owl2-1.0.9.dist-info/RECORD
