Metadata-Version: 2.3
Name: fuzzy-dl-owl2
Version: 1.0.9
Summary: A python porting of the Fuzzy Description Language (see https://www.umbertostraccia.it/cs/software/fuzzyDL/fuzzyDL.html) and the Fuzzy OWL 2 framework (see https://www.umbertostraccia.it/cs/software/FuzzyOWL/index.html).
License: CC-BY-SA-4.0
Author: Giuseppe Filippone
Author-email: filipponegiuseppe94@gmail.com
Requires-Python: >=3.11,<4.0
Classifier: License :: Other/Proprietary License
Classifier: Programming Language :: Python :: 3
Classifier: Programming Language :: Python :: 3.11
Classifier: Programming Language :: Python :: 3.12
Classifier: Programming Language :: Python :: 3.13
Requires-Dist: networkx (>=3.3,<4.0)
Requires-Dist: owlready2 (>=0.47,<0.48)
Requires-Dist: pyowl2 (>=1.0.3,<2.0.0)
Requires-Dist: pyparsing (>=3.2.3,<4.0.0)
Requires-Dist: rdflib (>=7.1.4,<8.0.0)
Requires-Dist: setuptools (>=80.8.0,<81.0.0)
Requires-Dist: sortedcontainers (>=2.4.0,<3.0.0)
Requires-Dist: trycast (>=1.2.0,<2.0.0)
Project-URL: Documentation, https://fuzzy-dl-owl2.readthedocs.io/en/latest/
Project-URL: Repository, https://github.com/giuseppefilippone/fuzzy_dl_owl2
